mann/__init__.py
mann/layers/FilterLayer.py
mann/layers/MaskedConv2D.py
mann/layers/MaskedDense.py
mann/layers/MultiConv2D.py
mann/layers/MultiDense.py
mann/layers/MultiMaskedConv2D.py
mann/layers/MultiMaskedDense.py
mann/layers/MultiMaxPool2D.py
mann/layers/SelectorLayer.py
mann/layers/SumLayer.py
mann/layers/__init__.py
mann/utils/__init__.py
mann/utils/utils.py
mann_m1mac-0.1.0.dist-info/LICENSE
mann_m1mac-0.1.0.dist-info/METADATA
mann_m1mac-0.1.0.dist-info/WHEEL
mann_m1mac-0.1.0.dist-info/top_level.txt
mann_m1mac-0.1.0.dist-info/RECORD
