Metadata-Version: 2.1
Name: mann-m1mac
Version: 0.1.0
Summary: Package containing utilities for implementing RSN2/MANN
Home-page: https://github.com/AISquaredInc/mann
Author: The AI Squared Team
Author-email: mann@squared.ai
License: Apache 2.0
Platform: UNKNOWN
License-File: LICENSE
